hw_deshrit/__init__.py
hw_deshrit/hw.py
helloworld_deshrit-0.0.4.dist-info/METADATA
helloworld_deshrit-0.0.4.dist-info/WHEEL
helloworld_deshrit-0.0.4.dist-info/top_level.txt
helloworld_deshrit-0.0.4.dist-info/RECORD
