Metadata-Version: 2.1
Name: helloworld_deshrit
Version: 0.0.4
Summary: This is just a simple hello world project
Home-page: https://github.com/deshrit/helloworld_deshrit
Author: Deshrit Baral
Author-email: deshritbaral@gmail.com
